amaps/__init__.py
amaps/client.py
amaps/distance_matrix.py
amaps/exceptions.py
amaptt/__init__.py
amaptt/client.py
amaptt/distance_matrix.py
amaptt/exceptions.py
amaptt-0.0.5.dist-info/LICENSE
amaptt-0.0.5.dist-info/METADATA
amaptt-0.0.5.dist-info/WHEEL
amaptt-0.0.5.dist-info/top_level.txt
amaptt-0.0.5.dist-info/RECORD
