Metadata-Version: 2.1
Name: amaptt
Version: 0.0.5
Summary: python api for amap travel time calc.
Home-page: https://github.com/iessen/amaptt.git
Author: ewg
Author-email: essen.wang@outlook.com
License: UNKNOWN
Platform: UNKNOWN
Classifier: Programming Language :: Python :: 3
Classifier: License :: OSI Approved :: MIT License
Classifier: Operating System :: OS Independent
Requires-Python: >=3.6
